gmn_data_store/__init__.py
gmn_data_store/__main__.py
gmn_data_store/controller.py
gmn_data_store/models.py
gmn_data_store/setup_database.py
gmn_data_store-0.0.2.dist-info/entry_points.txt
gmn_data_store-0.0.2.dist-info/LICENSE.rst
gmn_data_store-0.0.2.dist-info/WHEEL
gmn_data_store-0.0.2.dist-info/METADATA
gmn_data_store-0.0.2.dist-info/RECORD
