Metadata-Version: 2.1
Name: gmn-data-store
Version: 0.0.2
Summary: GMN Data Store
Home-page: https://github.com/rickybassom/gmn-data-store
License: MIT
Author: Ricky Bassom
Author-email: rickybas12@gmail.com
Requires-Python: >=3.7.1,<4.0.0
Classifier: Development Status :: 1 - Planning
Classifier: License :: OSI Approved :: MIT License
Classifier: Programming Language :: Python :: 3
Classifier: Programming Language :: Python :: 3.10
Classifier: Programming Language :: Python :: 3.8
Classifier: Programming Language :: Python :: 3.9
Requires-Dist: SQLAlchemy (==1.4.35)
Requires-Dist: click (==8.0.4)
Requires-Dist: gmn-python-api (==0.0.5)
Requires-Dist: sqlalchemy-views (==0.3.1)
Project-URL: Changelog, https://github.com/rickybassom/gmn-data-store/releases
Project-URL: Documentation, https://gmn-data-store.readthedocs.io
Project-URL: Repository, https://github.com/rickybassom/gmn-data-store
